aws_console_url_search/__init__.py
aws_console_url_search/_version.py
aws_console_url_search/api.py
aws_console_url_search/constants.py
aws_console_url_search/data.json
aws_console_url_search/dataset.py
aws_console_url_search/model.py
aws_console_url_search/paths.py
aws_console_url_search/region.tsv
aws_console_url_search/ui_def.py
aws_console_url_search/ui_init.py
aws_console_url_search/cli/__init__.py
aws_console_url_search/cli/main.py
aws_console_url_search/code/__init__.py
aws_console_url_search/code/console-urls-backup.json
aws_console_url_search/code/console-urls.json
aws_console_url_search/code/gen_code.py
aws_console_url_search/code/rank.rst
aws_console_url_search/docs/__init__.py
aws_console_url_search/tests/__init__.py
aws_console_url_search/tests/helper.py
aws_console_url_search/vendor/__init__.py
aws_console_url_search/vendor/pytest_cov_helper.py
aws_console_url_search-0.3.1.dist-info/AUTHORS.rst
aws_console_url_search-0.3.1.dist-info/LICENSE.txt
aws_console_url_search-0.3.1.dist-info/METADATA
aws_console_url_search-0.3.1.dist-info/WHEEL
aws_console_url_search-0.3.1.dist-info/entry_points.txt
aws_console_url_search-0.3.1.dist-info/top_level.txt
aws_console_url_search-0.3.1.dist-info/RECORD
